dh_json_logic/__init__.py
dh_json_logic-1.2.2.dist-info/LICENSE
dh_json_logic-1.2.2.dist-info/METADATA
dh_json_logic-1.2.2.dist-info/WHEEL
dh_json_logic-1.2.2.dist-info/RECORD
