Metadata-Version: 2.1
Name: dh-json-logic
Version: 1.2.2
Summary: A fork of https://github.com/YaraslauZhylko/json-logic-py/
Home-page: https://github.com/dearhealth/json-logic-py
Author: dearhealth
Requires-Python: >=3.10,<4.0
Classifier: Programming Language :: Python :: 3
Classifier: Programming Language :: Python :: 3.10
Classifier: Programming Language :: Python :: 3.11
Project-URL: Repository, https://github.com/dearhealth/json-logic-py
